{
  "project_info": {
    "project_number": "475544686343",
    "project_id": "seeker-depd",
    "storage_bucket": "seeker-depd.appspot.com"
  },
  "client": [
    {
      "client_info": {
        "mobilesdk_app_id": "1:475544686343:android:944f22a58c5ed2ea9a7fa2",
        "android_client_info": {
          "package_name": "com.seeker.food"
        }
      },
      "oauth_client": [
        {
          "client_id": "475544686343-l0uuoqkite00rp78kg9hvv87bl9h2vc1.apps.googleusercontent.com",
          "client_type": 1,
          "android_info": {
            "package_name": "com.seeker.food",
            "certificate_hash": "30caa85fddfa15643544af236138a2e1ee29ed25"
          }
        },
        {
          "client_id": "475544686343-aq0lj2tr5665th1tdl29jm26n224erj1.apps.googleusercontent.com",
          "client_type": 3
        }
      ],
      "api_key": [
        {
          "current_key": "AIzaSyAdpII7emuNGYQa1zr7k_7o_rQxTjAbwdk"
        }
      ],
      "services": {
        "appinvite_service": {
          "other_platform_oauth_client": [
            {
              "client_id": "475544686343-aq0lj2tr5665th1tdl29jm26n224erj1.apps.googleusercontent.com",
              "client_type": 3
            }
          ]
        }
      }
    }
  ],
  "configuration_version": "1"
}